placeholder/__init__.py
placeholder/compute_frameworks/__init__.py
placeholder/compute_frameworks/my_plugin/__init__.py
placeholder/compute_frameworks/my_plugin/my_compute_framework.py
placeholder/compute_frameworks/my_plugin/tests/__init__.py
placeholder/compute_frameworks/my_plugin/tests/test_my_compute_framework.py
placeholder/extenders/__init__.py
placeholder/extenders/my_plugin/__init__.py
placeholder/extenders/my_plugin/my_extender.py
placeholder/extenders/my_plugin/tests/__init__.py
placeholder/extenders/my_plugin/tests/test_my_extender.py
placeholder/feature_groups/__init__.py
placeholder/feature_groups/my_plugin/__init__.py
placeholder/feature_groups/my_plugin/my_feature_group.py
placeholder/feature_groups/my_plugin/tests/__init__.py
placeholder/feature_groups/my_plugin/tests/test_my_feature_group.py
placeholder_my_plugin-0.2.3.dist-info/licenses/LICENSE
placeholder_my_plugin-0.2.3.dist-info/METADATA
placeholder_my_plugin-0.2.3.dist-info/WHEEL
placeholder_my_plugin-0.2.3.dist-info/top_level.txt
placeholder_my_plugin-0.2.3.dist-info/RECORD
